docs/source/conf.py
eigensdk/__init__.py
eigensdk/py.typed
eigensdk/types_.py
eigensdk/chainio/__init__.py
eigensdk/chainio/utils.py
eigensdk/chainio/clients/__init__.py
eigensdk/chainio/clients/builder.py
eigensdk/chainio/clients/avsregistry/__init__.py
eigensdk/chainio/clients/avsregistry/reader.py
eigensdk/chainio/clients/avsregistry/writer.py
eigensdk/chainio/clients/elcontracts/__init__.py
eigensdk/chainio/clients/elcontracts/reader.py
eigensdk/chainio/clients/elcontracts/writer.py
eigensdk/contracts/ABIs.py
eigensdk/contracts/__init__.py
eigensdk/contracts/ABI/AVSDirectory.json
eigensdk/contracts/ABI/AllocationManager.json
eigensdk/contracts/ABI/BLSApkRegistry.json
eigensdk/contracts/ABI/DelegationManager.json
eigensdk/contracts/ABI/IERC20.json
eigensdk/contracts/ABI/IStrategy.json
eigensdk/contracts/ABI/OperatorStateRetriever.json
eigensdk/contracts/ABI/PermissionController.json
eigensdk/contracts/ABI/RegistryCoordinator.json
eigensdk/contracts/ABI/RewardsCoordinator.json
eigensdk/contracts/ABI/ServiceManagerBase.json
eigensdk/contracts/ABI/StakeRegistry.json
eigensdk/contracts/ABI/StrategyManager.json
eigensdk/crypto/__init__.py
eigensdk/crypto/bls/__init__.py
eigensdk/crypto/bls/attestation.py
eigensdk/crypto/bn256/__init__.py
eigensdk/crypto/bn256/utils.py
mcl/__init__.py
mcl/builder.py
mcl/consts.py
mcl/hook.py
mcl/utils.py
mcl/structures/Fp.py
mcl/structures/Fp2.py
mcl/structures/Fr.py
mcl/structures/G1.py
mcl/structures/G2.py
mcl/structures/GT.py
mcl/structures/__init__.py
mcl/structures/base.py
tests/__init__.py
tests/builder.py
tests/chainio/test_avs_reader.py
tests/chainio/test_avs_writer.py
tests/chainio/test_el_reader.py
tests/chainio/test_el_writer.py
tests/keys/aggregator.ecdsa.key.json
tests/keys/test.bls.key.json
tests/keys/test.ecdsa.key.json
eigensdk-0.1.0.dist-info/METADATA
eigensdk-0.1.0.dist-info/WHEEL
eigensdk-0.1.0.dist-info/top_level.txt
eigensdk-0.1.0.dist-info/RECORD
