Metadata-Version: 2.4
Name: eigensdk
Version: 0.1.0
Summary: A Python SDK for developing EigenLayer AVS.
Author-email: Abram Symons <abramsymons@gmail.com>
Maintainer-email: Abram Symons <abramsymons@gmail.com>
License-Expression: MIT
Project-URL: Homepage, https://github.com/zellular-xyz/eigensdk-python
Classifier: Programming Language :: Python :: 3
Classifier: Operating System :: OS Independent
Requires-Python: >=3.11
Requires-Dist: web3
Requires-Dist: python-dotenv==1.0.1
Provides-Extra: dev
Requires-Dist: pytest>=7.0.0; extra == "dev"
Requires-Dist: pytest-mock>=3.10.0; extra == "dev"
Requires-Dist: black>=23.3.0; extra == "dev"
Requires-Dist: flake8>=6.0.0; extra == "dev"
Requires-Dist: isort>=5.12.0; extra == "dev"
Requires-Dist: pre-commit>=3.4.0; extra == "dev"
Requires-Dist: mypy>=1.4.0; extra == "dev"
Requires-Dist: pytest-order>=1.3.0; extra == "dev"
Requires-Dist: PyYAML>=6.0.0; extra == "dev"
Requires-Dist: twine; extra == "dev"
Requires-Dist: build; extra == "dev"
